databaseautomationry/__init__.py
databaseautomationry/mongo_crud.py
databaseautomationry-0.0.1.dist-info/METADATA
databaseautomationry-0.0.1.dist-info/WHEEL
databaseautomationry-0.0.1.dist-info/top_level.txt
databaseautomationry-0.0.1.dist-info/RECORD
